{
  "address": "mZhPGteS36G7FhMTcRofLQU8ocBNAsGq7u8SKSHfL2X",
  "metadata": {
    "name": "hyperlane_adapter",
    "version": "0.1.0",
    "spec": "0.1.0",
    "description": "Created with Anchor"
  },
  "instructions": [
    {
      "name": "initialize",
      "discriminator": [
        175,
        175,
        109,
        31,
        13,
        152,
        155,
        237
      ],
      "accounts": [
        {
          "name": "admin",
          "writable": true,
          "signer": true
        },
        {
          "name": "hyperlane_global",
          "writable": true,
          "pda": {
            "seeds": [
              {
                "kind": "const",
                "value": [
                  103,
                  108,
                  111,
                  98,
                  97,
                  108
                ]
              }
            ]
          }
        },
        {
          "name": "account_metas_data",
          "writable": true,
          "pda": {
            "seeds": [
              {
                "kind": "const",
                "value": [
                  104,
                  121,
                  112,
                  101,
                  114,
                  108,
                  97,
                  110,
                  101,
                  95,
                  109,
                  101,
                  115,
                  115,
                  97,
                  103,
                  101,
                  95,
                  114,
                  101,
                  99,
                  105,
                  112,
                  105,
                  101,
                  110,
                  116
                ]
              },
              {
                "kind": "const",
                "value": [
                  45
                ]
              },
              {
                "kind": "const",
                "value": [
                  104,
                  97,
                  110,
                  100,
                  108,
                  101
                ]
              },
              {
                "kind": "const",
                "value": [
                  45
                ]
              },
              {
                "kind": "const",
                "value": [
                  97,
                  99,
                  99,
                  111,
                  117,
                  110,
                  116,
                  95,
                  109,
                  101,
                  116,
                  97,
                  115
                ]
              }
            ]
          }
        },
        {
          "name": "system_program",
          "address": "11111111111111111111111111111111"
        }
      ],
      "args": []
    },
    {
      "name": "receive_message",
      "discriminator": [
        33,
        210,
        5,
        66,
        196,
        212,
        239,
        142
      ],
      "accounts": [
        {
          "name": "hyperlane_process_authority",
          "writable": true,
          "signer": true,
          "pda": {
            "seeds": [
              {
                "kind": "const",
                "value": [
                  104,
                  121,
                  112,
                  101,
                  114,
                  108,
                  97,
                  110,
                  101
                ]
              },
              {
                "kind": "const",
                "value": [
                  45
                ]
              },
              {
                "kind": "const",
                "value": [
                  112,
                  114,
                  111,
                  99,
                  101,
                  115,
                  115,
                  95,
                  97,
                  117,
                  116,
                  104,
                  111,
                  114,
                  105,
                  116,
                  121
                ]
              },
              {
                "kind": "const",
                "value": [
                  45
                ]
              },
              {
                "kind": "const",
                "value": [
                  11,
                  106,
                  134,
                  128,
                  106,
                  3,
                  84,
                  200,
                  43,
                  143,
                  4,
                  158,
                  183,
                  93,
                  156,
                  151,
                  227,
                  112,
                  166,
                  240,
                  192,
                  207,
                  161,
                  95,
                  71,
                  144,
                  156,
                  63,
                  225,
                  200,
                  247,
                  148
                ]
              }
            ],
            "program": {
              "kind": "const",
              "value": [
                194,
                54,
                80,
                12,
                241,
                12,
                64,
                157,
                245,
                102,
                177,
                65,
                91,
                153,
                103,
                156,
                146,
                133,
                7,
                43,
                248,
                86,
                254,
                49,
                27,
                60,
                193,
                187,
                148,
                98,
                121,
                165
              ]
            }
          }
        },
        {
          "name": "hyperlane_adapter_authority",
          "docs": [
            "Payer for Portal CPI (needs to be funded)"
          ],
          "writable": true,
          "pda": {
            "seeds": [
              {
                "kind": "const",
                "value": [
                  97,
                  117,
                  116,
                  104,
                  111,
                  114,
                  105,
                  116,
                  121
                ]
              }
            ]
          }
        },
        {
          "name": "hyperlane_global",
          "pda": {
            "seeds": [
              {
                "kind": "const",
                "value": [
                  103,
                  108,
                  111,
                  98,
                  97,
                  108
                ]
              }
            ]
          }
        },
        {
          "name": "messenger_authority",
          "pda": {
            "seeds": [
              {
                "kind": "const",
                "value": [
                  97,
                  117,
                  116,
                  104,
                  111,
                  114,
                  105,
                  116,
                  121
                ]
              }
            ],
            "program": {
              "kind": "const",
              "value": [
                5,
                96,
                71,
                38,
                195,
                17,
                0,
                131,
                79,
                49,
                225,
                51,
                140,
                91,
                229,
                193,
                101,
                155,
                214,
                243,
                111,
                176,
                88,
                151,
                248,
                178,
                69,
                151,
                27,
                53,
                202,
                23
              ]
            }
          }
        },
        {
          "name": "portal_program",
          "address": "MzBrgc8yXBj4P16GTkcSyDZkEQZB9qDqf3fh9bByJce"
        },
        {
          "name": "system_program",
          "address": "11111111111111111111111111111111"
        }
      ],
      "args": [
        {
          "name": "origin",
          "type": "u32"
        },
        {
          "name": "sender",
          "type": {
            "array": [
              "u8",
              32
            ]
          }
        },
        {
          "name": "message",
          "type": "bytes"
        }
      ]
    },
    {
      "name": "receive_message_metas",
      "discriminator": [
        194,
        141,
        30,
        82,
        241,
        41,
        169,
        52
      ],
      "accounts": [
        {
          "name": "account_metas_data",
          "pda": {
            "seeds": [
              {
                "kind": "const",
                "value": [
                  104,
                  121,
                  112,
                  101,
                  114,
                  108,
                  97,
                  110,
                  101,
                  95,
                  109,
                  101,
                  115,
                  115,
                  97,
                  103,
                  101,
                  95,
                  114,
                  101,
                  99,
                  105,
                  112,
                  105,
                  101,
                  110,
                  116
                ]
              },
              {
                "kind": "const",
                "value": [
                  45
                ]
              },
              {
                "kind": "const",
                "value": [
                  104,
                  97,
                  110,
                  100,
                  108,
                  101
                ]
              },
              {
                "kind": "const",
                "value": [
                  45
                ]
              },
              {
                "kind": "const",
                "value": [
                  97,
                  99,
                  99,
                  111,
                  117,
                  110,
                  116,
                  95,
                  109,
                  101,
                  116,
                  97,
                  115
                ]
              }
            ]
          }
        }
      ],
      "args": [
        {
          "name": "origin",
          "type": "u32"
        },
        {
          "name": "sender",
          "type": {
            "array": [
              "u8",
              32
            ]
          }
        },
        {
          "name": "message",
          "type": "bytes"
        }
      ]
    },
    {
      "name": "send_message",
      "discriminator": [
        57,
        40,
        34,
        178,
        189,
        10,
        65,
        26
      ],
      "accounts": [
        {
          "name": "payer",
          "writable": true,
          "signer": true
        },
        {
          "name": "hyperlane_global",
          "pda": {
            "seeds": [
              {
                "kind": "const",
                "value": [
                  103,
                  108,
                  111,
                  98,
                  97,
                  108
                ]
              }
            ]
          }
        },
        {
          "name": "messenger_authority",
          "docs": [
            "Only relay messages coming from the Portal"
          ],
          "signer": true,
          "pda": {
            "seeds": [
              {
                "kind": "const",
                "value": [
                  97,
                  117,
                  116,
                  104,
                  111,
                  114,
                  105,
                  116,
                  121
                ]
              }
            ],
            "program": {
              "kind": "const",
              "value": [
                5,
                96,
                71,
                38,
                195,
                17,
                0,
                131,
                79,
                49,
                225,
                51,
                140,
                91,
                229,
                193,
                101,
                155,
                214,
                243,
                111,
                176,
                88,
                151,
                248,
                178,
                69,
                151,
                27,
                53,
                202,
                23
              ]
            }
          }
        },
        {
          "name": "mailbox_outbox",
          "writable": true,
          "pda": {
            "seeds": [
              {
                "kind": "const",
                "value": [
                  104,
                  121,
                  112,
                  101,
                  114,
                  108,
                  97,
                  110,
                  101
                ]
              },
              {
                "kind": "const",
                "value": [
                  45
                ]
              },
              {
                "kind": "const",
                "value": [
                  111,
                  117,
                  116,
                  98,
                  111,
                  120
                ]
              }
            ],
            "program": {
              "kind": "account",
              "path": "mailbox_program"
            }
          }
        },
        {
          "name": "dispatch_authority",
          "pda": {
            "seeds": [
              {
                "kind": "const",
                "value": [
                  104,
                  121,
                  112,
                  101,
                  114,
                  108,
                  97,
                  110,
                  101,
                  95,
                  100,
                  105,
                  115,
                  112,
                  97,
                  116,
                  99,
                  104,
                  101,
                  114
                ]
              },
              {
                "kind": "const",
                "value": [
                  45
                ]
              },
              {
                "kind": "const",
                "value": [
                  100,
                  105,
                  115,
                  112,
                  97,
                  116,
                  99,
                  104,
                  95,
                  97,
                  117,
                  116,
                  104,
                  111,
                  114,
                  105,
                  116,
                  121
                ]
              }
            ]
          }
        },
        {
          "name": "unique_message",
          "signer": true
        },
        {
          "name": "dispatched_message",
          "pda": {
            "seeds": [
              {
                "kind": "const",
                "value": [
                  104,
                  121,
                  112,
                  101,
                  114,
                  108,
                  97,
                  110,
                  101
                ]
              },
              {
                "kind": "const",
                "value": [
                  45
                ]
              },
              {
                "kind": "const",
                "value": [
                  100,
                  105,
                  115,
                  112,
                  97,
                  116,
                  99,
                  104,
                  101,
                  100,
                  95,
                  109,
                  101,
                  115,
                  115,
                  97,
                  103,
                  101
                ]
              },
              {
                "kind": "const",
                "value": [
                  45
                ]
              },
              {
                "kind": "account",
                "path": "unique_message"
              }
            ],
            "program": {
              "kind": "account",
              "path": "mailbox_program"
            }
          }
        },
        {
          "name": "mailbox_program",
          "address": "E588QtVUvresuXq2KoNEwAmoifCzYGpRBdHByN9KQMbi"
        },
        {
          "name": "spl_noop_program",
          "address": "noopb9bkMVfRPU8AsbpTUg8AQkHtKwMYZiFUjNRtMmV"
        },
        {
          "name": "system_program",
          "address": "11111111111111111111111111111111"
        }
      ],
      "args": [
        {
          "name": "message",
          "type": "bytes"
        },
        {
          "name": "destination_chain_id",
          "type": "u32"
        }
      ]
    }
  ],
  "accounts": [
    {
      "name": "AccountMetasData",
      "discriminator": [
        18,
        230,
        15,
        151,
        89,
        53,
        116,
        8
      ]
    },
    {
      "name": "HyperlaneGlobal",
      "discriminator": [
        139,
        60,
        79,
        223,
        221,
        146,
        42,
        102
      ]
    }
  ],
  "types": [
    {
      "name": "AccountMetasData",
      "type": {
        "kind": "struct",
        "fields": [
          {
            "name": "bump",
            "type": "u8"
          }
        ]
      }
    },
    {
      "name": "HyperlaneGlobal",
      "type": {
        "kind": "struct",
        "fields": [
          {
            "name": "bump",
            "type": "u8"
          },
          {
            "name": "admin",
            "type": "pubkey"
          },
          {
            "name": "paused",
            "type": "bool"
          },
          {
            "name": "peers",
            "type": {
              "vec": {
                "defined": {
                  "name": "Peer"
                }
              }
            }
          }
        ]
      }
    },
    {
      "name": "Peer",
      "type": {
        "kind": "struct",
        "fields": [
          {
            "name": "address",
            "type": {
              "array": [
                "u8",
                32
              ]
            }
          },
          {
            "name": "chain_id",
            "type": "u32"
          }
        ]
      }
    }
  ],
  "constants": [
    {
      "name": "DASH_SEED",
      "type": "bytes",
      "value": "[45]"
    },
    {
      "name": "DISPATCHED_MESSGAGE_SEED",
      "type": "bytes",
      "value": "[100, 105, 115, 112, 97, 116, 99, 104, 101, 100, 95, 109, 101, 115, 115, 97, 103, 101]"
    },
    {
      "name": "DISPATCH_SEED_1",
      "type": "bytes",
      "value": "[104, 121, 112, 101, 114, 108, 97, 110, 101, 95, 100, 105, 115, 112, 97, 116, 99, 104, 101, 114]"
    },
    {
      "name": "DISPATCH_SEED_2",
      "type": "bytes",
      "value": "[100, 105, 115, 112, 97, 116, 99, 104, 95, 97, 117, 116, 104, 111, 114, 105, 116, 121]"
    },
    {
      "name": "GLOBAL_SEED",
      "type": "bytes",
      "value": "[103, 108, 111, 98, 97, 108]"
    },
    {
      "name": "HYPERLANE_SEED",
      "type": "bytes",
      "value": "[104, 121, 112, 101, 114, 108, 97, 110, 101]"
    },
    {
      "name": "METADATA_SEED_1",
      "type": "bytes",
      "value": "[104, 121, 112, 101, 114, 108, 97, 110, 101, 95, 109, 101, 115, 115, 97, 103, 101, 95, 114, 101, 99, 105, 112, 105, 101, 110, 116]"
    },
    {
      "name": "METADATA_SEED_2",
      "type": "bytes",
      "value": "[104, 97, 110, 100, 108, 101]"
    },
    {
      "name": "METADATA_SEED_3",
      "type": "bytes",
      "value": "[97, 99, 99, 111, 117, 110, 116, 95, 109, 101, 116, 97, 115]"
    },
    {
      "name": "OUTBOX_SEED",
      "type": "bytes",
      "value": "[111, 117, 116, 98, 111, 120]"
    },
    {
      "name": "PROCESS_AUTHORITY",
      "type": "bytes",
      "value": "[112, 114, 111, 99, 101, 115, 115, 95, 97, 117, 116, 104, 111, 114, 105, 116, 121]"
    }
  ]
}